inshorts.py
inshorts-2021.1.dist-info/LICENSE
inshorts-2021.1.dist-info/WHEEL
inshorts-2021.1.dist-info/METADATA
inshorts-2021.1.dist-info/RECORD
