Metadata-Version: 2.1
Name: inshorts
Version: 2021.1
Summary: cli for inshorts
License: MIT
Author: Sayan Goswami
Author-email: goswami.sayan47@gmail.com
Requires-Python: >=3.9,<4.0
Classifier: License :: OSI Approved :: MIT License
Classifier: Programming Language :: Python :: 3
Classifier: Programming Language :: Python :: 3.9
Requires-Dist: beautifulsoup4 (>=4.9.3,<5.0.0)
Requires-Dist: click (>=7.1.2,<8.0.0)
Requires-Dist: colorama (>=0.4.4,<0.5.0)
Requires-Dist: requests (>=2.25.1,<3.0.0)
